chartjs_engine
