Metadata-Version: 1.0
Name: django-chartjs-engine
Version: 0.0.2
Summary: Django app to build chartjs javascript charts
Home-page: https://github.com/deltaskelta/django-chartjs_engine
Author: Jeff Willette
Author-email: jrwillette88@gmail.com
License: UNKNOWN
Keywords: django,chartjs,javascript,charts
Platform: UNKNOWN
